{
  "schema_version": "1.0",
  "tenant": {
    "slug": "tuotu",
    "name": "拓浙 AI 生态",
    "type": "enterprise_demo"
  },
  "company": {
    "slug": "tuotu",
    "name": "拓浙 AI 生态",
    "industry": "AI 教育与产学合作"
  },
  "card": {
    "slug": "tuotu",
    "status": "published"
  },
  "knowledge_version": "2026.07-v0.1",
  "documents": [
    {
      "external_id": "faq-overview",
      "source_type": "faq",
      "title": "拓浙 AI 生态是什么？",
      "visibility": "public",
      "content": "拓浙 AI 生态由拓途浙享网站、学习与项目执行体系、浙客松品牌活动及产学合作路径组成。它希望让学生从 AI 学习进入真实项目，并沉淀可展示的成果。",
      "metadata": {
        "source_label": "2026 年 7 月规划稿 P010-P016、T03-T04",
        "tags": ["项目介绍", "生态", "定位"]
      }
    },
    {
      "external_id": "faq-platform",
      "source_type": "faq",
      "title": "拓途浙享网站有什么作用？",
      "visibility": "public",
      "content": "网站是生态的数字入口。现有资料展示了校园活动聚合与 AI 社区界面，并规划项目广场和黑客松成果页，用于发现机会、沉淀内容、组织项目和展示成果。",
      "metadata": {
        "source_label": "2026 年 7 月规划稿 P017-P039；规划书(3)产品截图",
        "source_url": "https://tuotuzju.com",
        "tags": ["网站", "平台", "功能"]
      }
    },
    {
      "external_id": "faq-beginner",
      "source_type": "faq",
      "title": "零基础学生可以参加吗？",
      "visibility": "public",
      "content": "可以。学习体系规划提供 AI 工具、AI 编程、智能体入门、低门槛工作坊和基础项目训练。具体课程、招新与报名时间仍需以项目方当期通知为准。",
      "metadata": {
        "source_label": "2026 年 7 月规划稿 P043-P051",
        "tags": ["零基础", "学习", "报名"]
      }
    },
    {
      "external_id": "faq-technical",
      "source_type": "faq",
      "title": "有技术基础的学生能做什么？",
      "visibility": "public",
      "content": "可以关注技术交流、项目组队、真实课题和浙客松。规划中的技术层面向具备开发、产品或协作能力的学生，具体选拔与任务以当期项目要求为准。",
      "metadata": {
        "source_label": "2026 年 7 月规划稿 P052-P059",
        "tags": ["技术", "开发", "项目"]
      }
    },
    {
      "external_id": "faq-hackathon",
      "source_type": "faq",
      "title": "浙客松是什么？",
      "visibility": "public",
      "content": "浙客松是围绕 AI 全栈技术和真实场景问题进行项目闭环的系列活动。材料记录首届约 300 人报名、100 人参赛，并规划医学、量化、硬件、旅游、教育和企业服务等主题。",
      "metadata": {
        "source_label": "2026 年 7 月规划稿 P070-P093、P110",
        "tags": ["浙客松", "黑客松", "活动"]
      }
    },
    {
      "external_id": "faq-cooperation",
      "source_type": "faq",
      "title": "企业如何合作？",
      "visibility": "public",
      "content": "材料规划企业可提供真实需求、项目或赛题，参与成果评价与人才交流。具体费用、周期、知识产权、保密和验收方式尚未提供，需要由项目方进一步确认。",
      "metadata": {
        "source_label": "2026 年 7 月规划稿 P060-P067、P083-P087、T06",
        "tags": ["企业合作", "项目", "待确认"]
      }
    },
    {
      "external_id": "faq-metrics",
      "source_type": "faq",
      "title": "平台目前规模如何？",
      "visibility": "public",
      "content": "据 2026 年 7 月项目材料，平台注册用户 2300+、日均浏览 900+ 人次、累计收录 700+ 项校园活动，AI 微信交流群达到 500 人满额。这些不是实时接口数据，正式发布前需要复核统计口径。",
      "metadata": {
        "source_label": "2026 年 7 月规划稿 P105-P112",
        "tags": ["规模", "数据", "统计口径"]
      }
    },
    {
      "external_id": "faq-official",
      "source_type": "faq",
      "title": "这是浙江大学官方平台吗？",
      "visibility": "public",
      "content": "现有资料只描述以浙江大学为起点及相关校内支持，没有提供足以证明官方主体身份或官方授权的文件。正式身份应以项目方和相关单位确认的信息为准。",
      "metadata": {
        "source_label": "2026 年 7 月规划稿 P003、P011、P111-P112",
        "tags": ["官方身份", "授权", "事实边界"]
      }
    },
    {
      "external_id": "faq-opportunity",
      "source_type": "faq",
      "title": "是否保证实习、内推或就业？",
      "visibility": "public",
      "content": "不保证。资料表达的是择优连接相关机会，最终结果取决于合作方规则、项目表现和后续评估。样板不会作出录用、内推或就业结果承诺。",
      "metadata": {
        "source_label": "2026 年 7 月规划稿 P083-P087、T06",
        "tags": ["实习", "就业", "禁承诺"]
      }
    },
    {
      "external_id": "faq-contact",
      "source_type": "faq",
      "title": "如何加入或联系项目方？",
      "visibility": "public",
      "content": "现有资料没有提供可公开的联系人、电话、邮箱或正式入群入口。可以先访问 tuotuzju.com 了解公开信息，正式数智名片上线前仍需项目方补齐官方联系渠道。",
      "metadata": {
        "source_label": "三份项目资料联系人盘点；官网公开入口",
        "source_url": "https://tuotuzju.com",
        "tags": ["联系", "加入", "资料缺口"]
      }
    }
  ]
}
